python_imagemanipulating/__init__.py
python_imagemanipulating/effects.py
python_imagemanipulating-0.0.1.dist-info/METADATA
python_imagemanipulating-0.0.1.dist-info/WHEEL
python_imagemanipulating-0.0.1.dist-info/top_level.txt
python_imagemanipulating-0.0.1.dist-info/RECORD
