Metadata-Version: 2.1
Name: python-imagemanipulating
Version: 0.0.1
Summary: Easily manipulate images with python_imagemanipulating
Home-page: https://python_imagemanipulating.readthedocs.io/
Author: saucrio
License: MIT
Platform: UNKNOWN
Classifier: Intended Audience :: Developers
Classifier: License :: OSI Approved :: MIT License
Classifier: Programming Language :: Python
Classifier: Programming Language :: Python :: 3
Classifier: Programming Language :: Python :: 3.6
Classifier: Programming Language :: Python :: 3.7
Classifier: Programming Language :: Python :: 3.8
Classifier: Programming Language :: Python :: 3.9
Classifier: Operating System :: OS Independent
Requires-Dist: Pillow
Requires-Dist: requests
